{
    "name": "ddbctest",
    "description": " Hibernated",
    "authors": ["donglei"],
    "license": "Boost Software License (BSL 1.0)",
    "buildRequirements": ["allowWarnings"],
    "dependencies": {
        "entity": {"path": "../../"}
    },
    "targetType": "executable",
    "configurations": [
        {
            "name": "full",
            "versions": ["USE_MYSQL", "USE_SQLITE", "USE_PGSQL"],
            "subConfigurations": {
                "entity": "full"
            }
        },
        {
            "name": "MySQL",
            "versions": ["USE_MYSQL"],
            "subConfigurations": {
                "entity": "MySQL"
            }
        },
        {
            "name": "SQLite",
            "versions": ["USE_SQLITE"],
            "subConfigurations": {
                "entity": "SQLite"
            }
        },
        {
            "name": "PGSQL",
            "versions": ["USE_PGSQL"],
            "subConfigurations": {
                "entity": "PGSQL"
            }
        }
    ]
}
