{
    "name": "hunt-entity",
    "description": "Entity is an object-relational mapping (ORM) tool for the D programming language. Referring to the design idea of JPA. support PostgreSQL / MySQL.",
    "copyright": "Copyright (C) 2018-2019, HuntLabs",
    "homepage": "https://www.huntlabs.net",
    "license": "Apache-2.0",
    "versions": ["WITH_HUNT_ENTITY"],
    "dependencies": {
        "hunt-database": {"path": "../hunt-database"},
        "hunt-validation" : {"path": "../hunt-validation"}
    },
    "subConfigurations": {
        "hunt-database": "ssl"
    }
}

